drawpyo/__init__.py
drawpyo/file.py
drawpyo/page.py
drawpyo/xml_base.py
drawpyo/diagram/__init__.py
drawpyo/diagram/base_diagram.py
drawpyo/diagram/edges.py
drawpyo/diagram/extended_objects.py
drawpyo/diagram/objects.py
drawpyo/diagram/text_format.py
drawpyo/diagram_types/__init__.py
drawpyo/diagram_types/bar_chart.py
drawpyo/diagram_types/binary_tree.py
drawpyo/diagram_types/class_diagram.py
drawpyo/diagram_types/legend.py
drawpyo/diagram_types/pie_chart.py
drawpyo/diagram_types/tree.py
drawpyo/formatting_database/edge_styles.toml
drawpyo/formatting_database/line_styles.toml
drawpyo/shape_libraries/flowchart.toml
drawpyo/shape_libraries/general.toml
drawpyo/shape_libraries/infographics.toml
drawpyo/utils/__init__.py
drawpyo/utils/color_scheme.py
drawpyo/utils/logger.py
drawpyo/utils/standard_colors.py
drawpyo-0.2.4.dist-info/licenses/LICENSE
drawpyo-0.2.4.dist-info/WHEEL
drawpyo-0.2.4.dist-info/METADATA
drawpyo-0.2.4.dist-info/RECORD
