Metadata-Version: 2.4
Name: drawpyo
Version: 0.2.4
Summary: A Python library for programmatically generating Draw.io charts.
Keywords: draw.io,diagrams.net,diagrams
Author-email: Xander Cesari <xander@merriman.industries>
Requires-Python: >=3.10
Classifier: Programming Language :: Python :: 3
Classifier: License :: OSI Approved :: MIT License
Classifier: Operating System :: OS Independent
License-File: LICENSE
Requires-Dist: toml >= 0.10.2; python_version < '3.11'
Requires-Dist: pytest >= 7.0 ; extra == "dev"
Project-URL: Homepage, https://github.com/MerrimanInd/drawpyo
Project-URL: Issues, https://github.com/MerrimanInd/drawpyo/issues
Provides-Extra: dev
